shiftify/__init__.py
shiftify/csv_convertor.py
shiftify/json_convertor.py
shiftify-0.1.4.dist-info/licenses/LICENSE
shiftify-0.1.4.dist-info/METADATA
shiftify-0.1.4.dist-info/WHEEL
shiftify-0.1.4.dist-info/entry_points.txt
shiftify-0.1.4.dist-info/top_level.txt
shiftify-0.1.4.dist-info/RECORD
