Metadata-Version: 2.4
Name: Shiftify
Version: 0.1.4
Summary: A simple utility for converting formats to different and vice versa.
Home-page: http://github.com/abdulrafey38/shiftify
Author: Abdul Rafey
Author-email: abdulrafey38@gmail.com
Keywords: CSV,JSON,conversion,data transformation,file format,convert CSV to JSON,convert JSON to CSV,data interchange,CSV converter,JSON converter,data conversion,format switcher
License-File: LICENSE
Requires-Dist: ijson
Requires-Dist: PyYAML>=6.0
Requires-Dist: openpyxl
Requires-Dist: toml
Dynamic: author
Dynamic: author-email
Dynamic: description
Dynamic: description-content-type
Dynamic: home-page
Dynamic: keywords
Dynamic: license-file
Dynamic: requires-dist
Dynamic: summary
